odoo/addons/onchange_helper/README.rst
odoo/addons/onchange_helper/__init__.py
odoo/addons/onchange_helper/__manifest__.py
odoo/addons/onchange_helper/i18n/cs_CZ.po
odoo/addons/onchange_helper/i18n/de.po
odoo/addons/onchange_helper/i18n/es.po
odoo/addons/onchange_helper/i18n/es_AR.po
odoo/addons/onchange_helper/i18n/fr.po
odoo/addons/onchange_helper/i18n/hr.po
odoo/addons/onchange_helper/i18n/onchange_helper.pot
odoo/addons/onchange_helper/i18n/sl.po
odoo/addons/onchange_helper/i18n/zh_CN.po
odoo/addons/onchange_helper/models/__init__.py
odoo/addons/onchange_helper/models/base.py
odoo/addons/onchange_helper/readme/CONTRIBUTORS.rst
odoo/addons/onchange_helper/readme/DESCRIPTION.rst
odoo/addons/onchange_helper/readme/USAGE.rst
odoo/addons/onchange_helper/static/description/icon.png
odoo/addons/onchange_helper/static/description/index.html
odoo/addons/onchange_helper/tests/__init__.py
odoo/addons/onchange_helper/tests/test_onchange_helper.py
odoo13_addon_onchange_helper-13.0.1.1.0.dist-info/METADATA
odoo13_addon_onchange_helper-13.0.1.1.0.dist-info/WHEEL
odoo13_addon_onchange_helper-13.0.1.1.0.dist-info/top_level.txt
odoo13_addon_onchange_helper-13.0.1.1.0.dist-info/RECORD
